sensorthings/__init__.py
sensorthings/engine.py
sensorthings/factories.py
sensorthings/http.py
sensorthings/main.py
sensorthings/middleware.py
sensorthings/renderer.py
sensorthings/router.py
sensorthings/schemas.py
sensorthings/settings.py
sensorthings/components/__init__.py
sensorthings/components/field_schemas.py
sensorthings/components/datastreams/__init__.py
sensorthings/components/datastreams/engine.py
sensorthings/components/datastreams/schemas.py
sensorthings/components/datastreams/views.py
sensorthings/components/featuresofinterest/__init__.py
sensorthings/components/featuresofinterest/engine.py
sensorthings/components/featuresofinterest/schemas.py
sensorthings/components/featuresofinterest/views.py
sensorthings/components/historicallocations/__init__.py
sensorthings/components/historicallocations/engine.py
sensorthings/components/historicallocations/schemas.py
sensorthings/components/historicallocations/views.py
sensorthings/components/locations/__init__.py
sensorthings/components/locations/engine.py
sensorthings/components/locations/schemas.py
sensorthings/components/locations/views.py
sensorthings/components/observations/__init__.py
sensorthings/components/observations/engine.py
sensorthings/components/observations/schemas.py
sensorthings/components/observations/views.py
sensorthings/components/observedproperties/__init__.py
sensorthings/components/observedproperties/engine.py
sensorthings/components/observedproperties/schemas.py
sensorthings/components/observedproperties/views.py
sensorthings/components/root/__init__.py
sensorthings/components/root/schemas.py
sensorthings/components/root/views.py
sensorthings/components/sensors/__init__.py
sensorthings/components/sensors/engine.py
sensorthings/components/sensors/schemas.py
sensorthings/components/sensors/views.py
sensorthings/components/things/__init__.py
sensorthings/components/things/engine.py
sensorthings/components/things/schemas.py
sensorthings/components/things/views.py
hydroserver_sensorthings-0.4.2.dist-info/LICENSE
hydroserver_sensorthings-0.4.2.dist-info/METADATA
hydroserver_sensorthings-0.4.2.dist-info/WHEEL
hydroserver_sensorthings-0.4.2.dist-info/top_level.txt
hydroserver_sensorthings-0.4.2.dist-info/zip-safe
hydroserver_sensorthings-0.4.2.dist-info/RECORD
