Metadata-Version: 2.2
Name: hydroserver-sensorthings
Version: 0.4.2
Requires-Python: >=3.9
License-File: LICENSE
Requires-Dist: django>=3.1
Requires-Dist: django-ninja>=1.0
Requires-Dist: pydantic>=2.0.1
Requires-Dist: geojson-pydantic>=1.0
Requires-Dist: requests>=2
Requires-Dist: odata-query>=0.8.1
Requires-Dist: pytz>=2022.7.1
Requires-Dist: python-dateutil>=2.8.2
Requires-Dist: orjson>=3.9
Provides-Extra: docs
Requires-Dist: sphinx_autodoc_typehints; extra == "docs"
